{
  "backend": {
    "runs": [
      {
        "rps": 1441.54,
        "lat_avg_ms": 60.38,
        "lat_stdev_ms": 140.96,
        "lat_max_ms": 1690.0,
        "socket_errors": 25,
        "non2xx": 0
      },
      {
        "rps": 1450.81,
        "lat_avg_ms": 27.73,
        "lat_stdev_ms": 97.61,
        "lat_max_ms": 1700.0,
        "socket_errors": 12,
        "non2xx": 0
      },
      {
        "rps": 1499.6,
        "lat_avg_ms": 34.08,
        "lat_stdev_ms": 130.3,
        "lat_max_ms": 1730.0,
        "socket_errors": 16,
        "non2xx": 0
      }
    ],
    "avg": {
      "rps": 1463.9833333333333,
      "lat_avg_ms": 40.73,
      "lat_stdev_ms": 122.95666666666666,
      "lat_max_ms": 1706.6666666666667,
      "socket_errors": 53,
      "non2xx": 0
    }
  },
  "nginx": {
    "runs": [
      {
        "rps": 1510.81,
        "lat_avg_ms": 84.91,
        "lat_stdev_ms": 235.09,
        "lat_max_ms": 1880.0,
        "socket_errors": 28,
        "non2xx": 0
      },
      {
        "rps": 1517.67,
        "lat_avg_ms": 104.45,
        "lat_stdev_ms": 255.38,
        "lat_max_ms": 1860.0,
        "socket_errors": 28,
        "non2xx": 0
      },
      {
        "rps": 1415.02,
        "lat_avg_ms": 76.45,
        "lat_stdev_ms": 202.81,
        "lat_max_ms": 1860.0,
        "socket_errors": 22,
        "non2xx": 0
      }
    ],
    "avg": {
      "rps": 1481.1666666666667,
      "lat_avg_ms": 88.60333333333334,
      "lat_stdev_ms": 231.09333333333333,
      "lat_max_ms": 1866.6666666666667,
      "socket_errors": 78,
      "non2xx": 0
    }
  },
  "ultra": {
    "runs": [
      {
        "rps": 1506.8,
        "lat_avg_ms": 109.65,
        "lat_stdev_ms": 272.79,
        "lat_max_ms": 1890.0,
        "socket_errors": 27,
        "non2xx": 0
      },
      {
        "rps": 1472.26,
        "lat_avg_ms": 159.93,
        "lat_stdev_ms": 316.1,
        "lat_max_ms": 1890.0,
        "socket_errors": 43,
        "non2xx": 0
      },
      {
        "rps": 1545.32,
        "lat_avg_ms": 110.11,
        "lat_stdev_ms": 265.22,
        "lat_max_ms": 1880.0,
        "socket_errors": 31,
        "non2xx": 0
      }
    ],
    "avg": {
      "rps": 1508.1266666666668,
      "lat_avg_ms": 126.56333333333333,
      "lat_stdev_ms": 284.7033333333334,
      "lat_max_ms": 1886.6666666666667,
      "socket_errors": 101,
      "non2xx": 0
    }
  },
  "compare": {
    "ultra_vs_nginx_rps_ratio": 1.018201867896928
  }
}